django_luigi/__init__.py
django_luigi/admin.py
django_luigi/apps.py
django_luigi/django.py
django_luigi/models.py
django_luigi/tests.py
django_luigi/views.py
django_luigi/migrations/0001_initial.py
django_luigi/migrations/__init__.py
django_luigi-0.2.5.dist-info/DESCRIPTION.rst
django_luigi-0.2.5.dist-info/METADATA
django_luigi-0.2.5.dist-info/RECORD
django_luigi-0.2.5.dist-info/WHEEL
django_luigi-0.2.5.dist-info/metadata.json
django_luigi-0.2.5.dist-info/top_level.txt
